MANIFEST.in
anonymization_demo.xml
anonymization_view.xml
ir.model.fields.anonymization.csv
setup.py
./__init__.py
./__openerp__.py
./anonymization.py
i18n/anonymization.pot
i18n/ar.po
i18n/bg.po
i18n/ca.po
i18n/cs.po
i18n/da.po
i18n/de.po
i18n/en_GB.po
i18n/es.po
i18n/es_CR.po
i18n/es_EC.po
i18n/es_MX.po
i18n/es_PY.po
i18n/es_VE.po
i18n/et.po
i18n/fa.po
i18n/fi.po
i18n/fr.po
i18n/gl.po
i18n/hr.po
i18n/hu.po
i18n/it.po
i18n/ja.po
i18n/lv.po
i18n/mk.po
i18n/mn.po
i18n/nb.po
i18n/nl.po
i18n/pl.po
i18n/pt.po
i18n/pt_BR.po
i18n/ro.po
i18n/ru.po
i18n/sl.po
i18n/sq.po
i18n/sr@latin.po
i18n/sv.po
i18n/tr.po
i18n/zh_CN.po
i18n/zh_TW.po
images/anonymization1.jpeg
images/anonymization2.jpeg
images/anonymization3.jpeg
openerp_anonymization.egg-info/PKG-INFO
openerp_anonymization.egg-info/SOURCES.txt
openerp_anonymization.egg-info/dependency_links.txt
openerp_anonymization.egg-info/requires.txt
openerp_anonymization.egg-info/top_level.txt
security/ir.model.access.csv